DisnodeLogger/__init__.py
DisnodeLogger-0.4.dist-info/DESCRIPTION.rst
DisnodeLogger-0.4.dist-info/METADATA
DisnodeLogger-0.4.dist-info/RECORD
DisnodeLogger-0.4.dist-info/WHEEL
DisnodeLogger-0.4.dist-info/metadata.json
DisnodeLogger-0.4.dist-info/top_level.txt
