Metadata-Version: 2.0
Name: DisnodeLogger
Version: 0.4
Summary: UNKNOWN
Home-page: UNKNOWN
Author: Hazed SPaCEx
Author-email: UNKNOWN
License: MIT
Keywords: logger disnode
Platform: UNKNOWN
Requires-Dist: colorama
